pavan_housing/__init__.py
pavan_housing/config.py
pavan_housing/ingest_data.py
pavan_housing/logger.py
pavan_housing/methods.py
pavan_housing/predict.py
pavan_housing/train.py
pavan_housing-0.2.dist-info/METADATA
pavan_housing-0.2.dist-info/WHEEL
pavan_housing-0.2.dist-info/top_level.txt
pavan_housing-0.2.dist-info/RECORD
