Metadata-Version: 2.1
Name: pavan-housing
Version: 0.2
Summary: 'A housing package to predict the price of houses in california'
Author-email: Pavan Bongu <pavan.bongu@tigeranalytics.com>
Project-URL: Homepage, https://github.com/pavanbongu7/mle-training
Classifier: Programming Language :: Python :: 3
Classifier: License :: OSI Approved :: MIT License
Classifier: Operating System :: OS Independent
Requires-Python: >=3.7
